sparrow/__init__.py
sparrow/config.py
sparrow/layers.py
sparrow/models.py
sparrow_mlp-3.0.2.dist-info/LICENSE
sparrow_mlp-3.0.2.dist-info/METADATA
sparrow_mlp-3.0.2.dist-info/WHEEL
sparrow_mlp-3.0.2.dist-info/top_level.txt
sparrow_mlp-3.0.2.dist-info/RECORD
