Metadata-Version: 2.2
Name: sparrow-mlp
Version: 3.0.2
Summary: A library for building dynamic and self-pruning MLPs with Mixture of Experts and Layer Skipping.
Home-page: https://github.com/amirahali2008wp-sudo/sparrow-mlp
Author: AmirReza
Author-email: amirrezaahali@gmail.com
Classifier: Programming Language :: Python :: 3
Classifier: License :: OSI Approved :: MIT License
Classifier: Operating System :: OS Independent
Classifier: Intended Audience :: Developers
Classifier: Topic :: Scientific/Engineering :: Artificial Intelligence
Requires-Python: >=3.7
License-File: LICENSE
Requires-Dist: torch>=1.9.0
Dynamic: author
Dynamic: author-email
Dynamic: classifier
Dynamic: description
Dynamic: description-content-type
Dynamic: home-page
Dynamic: requires-dist
Dynamic: requires-python
Dynamic: summary
